<beast version='2.0' namespace= 'master
                                             :master.model
                                             :master.conditions
                                             :master.outputs
                                             :master.postprocessors'>
              <run spec='InheritanceEnsemble' 
                   simulationTime='0.581857432709638'
                   samplePopulationSizes='true' 
                   nTraj='5'
                   verbosity='1'  maxConditionRejects='50'>
            
                <model spec='Model' id='model'>
                  <population spec='Population' id='S' populationName='S' />
                  <population spec='Population' id='I' populationName='I' />
                  <population spec='Population' id='R' populationName='R' />
                  <population spec='Population' id='I_sample' populationName='I_sample' />
            
                  <reaction spec='Reaction' reactionName='Infection' rate='2.53900322790369'>
                    S + I -> 2I
                  </reaction>
                  <reaction spec='Reaction' reactionName='Recovery' rate='3.58366038332454'>
                    I -> R
                  </reaction>
                  <reaction spec='Reaction' reactionName='Sampling' rate='3.07369055155815'>
                    I:1 -> I_sample:1
                  </reaction>
                </model>
            
                <initialState spec='InitState'>
                  <populationSize spec='PopulationSize' population='@S' size='10039.7803217143'/>
                  <populationSize spec='PopulationSize' population='@I_sample' size='0'/>
                  <populationSize spec='PopulationSize' population='@R' size='0'/>
                  <lineageSeed spec='Individual' population='@I'/>
                </initialState>

                <lineageEndCondition spec='LineageEndCondition' population='@I' nLineages='0' isRejection='true'>
                </lineageEndCondition>
               
                <inheritancePostProcessor spec='LineageSampler' samplingTime='0.1'>
                  <populationSize spec='PopulationSize' population='@I_sample' size='100'/>
                </inheritancePostProcessor>
            
                <output spec='NewickOutput' fileName='/tmp/RtmpovVooX/temp2a3f4a20809f.newick' collapseSingleChildNodes='true'/>
              </run>
            </beast>
